README.rst
setup.py
TimedDict/__init__.py
TimedDict/timeddict.py
TimedDict.egg-info/PKG-INFO
TimedDict.egg-info/SOURCES.txt
TimedDict.egg-info/dependency_links.txt
TimedDict.egg-info/top_level.txt