Metadata-Version: 1.0
Name: TimedDict
Version: 0.2.3
Summary: Extending the dict data type, with a rolling window feature, that automatically purge elements falling outside the defined window.
Home-page: https://github.com/hjortlund/TimedDict
Author: Christoffer Hjortlund
Author-email: hjortlund@gmail.com
License: MIT
Platform: UNKNOWN
